[
  {
    "a": "go into the past and meet your ancestors?",
    "b": "go into the future and meet your great-great-grandchildren?"
  },
  {
    "a": "have more time?",
    "b": "have more money?"
  },
  {
    "a": "have a rewind button on your life?",
    "b": "have a pause button on your life?"
  },
  {
    "a": "be able to talk with animals?",
    "b": "speak all foreign languages?"
  },
  {
    "a": "win the lottery?",
    "b": "live twice as long?"
  },
  {
    "a": "feel worse if no one showed up to your wedding?",
    "b": "feel worse if no one showed up to your funeral?"
  },
  {
    "a": "be without internet for a week?",
    "b": "be without your phone for a week?"
  },
  {
    "a": "be able to travel everywhere?",
    "b": "be rich but cannot leave your house?"
  },
  {
    "a": "lose your vision?",
    "b": "lose your hearing?"
  },
  {
    "a": "work more hours per day but fewer days?",
    "b": "work fewer hours per day but more days?"
  },
  {
    "a": "listen to music from the '80s?",
    "b": "listen to music from today?"
  },
  {
    "a": "become someone else?",
    "b": "just stay you?"
  },
  {
    "a": "be Batman?",
    "b": "be Spiderman?"
  },
  {
    "a": "be stuck on a broken ski lift?",
    "b": "be stuck in a broken elevator?"
  },
  {
    "a": "receive cash for your birthday?",
    "b": "receive gifts for your birthday?"
  },
  {
    "a": "go to a movie alone?",
    "b": "go to dinner alone?"
  },
  {
    "a": "always say everything on your mind?",
    "b": "never speak again?"
  },
  {
    "a": "make a phone call?",
    "b": "send a text?"
  },
  {
    "a": "read an awesome book?",
    "b": "watch a good movie?"
  },
  {
    "a": "be the most popular person at work or school?",
    "b": "be the smartest person at work or school?"
  },
  {
    "a": "put a stop to war?",
    "b": "end world hunger?"
  },
  {
    "a": "spend the night in a luxury hotel room?",
    "b": "spend the night camping surrounded by beautiful scenery?"
  },
  {
    "a": "explore space?",
    "b": "explore the ocean?"
  },
  {
    "a": "go deep-sea diving?",
    "b": "go bungee jumping?"
  },
  {
    "a": "be a kid your whole life?",
    "b": "be an adult your whole life?"
  },
  {
    "a": "go on a cruise with friends?",
    "b": "go on a cruise with your spouse?"
  },
  {
    "a": "lose your keys?",
    "b": "lose your cell phone?"
  },
  {
    "a": "eat a meal of cow tongue?",
    "b": "eat a meal of octopus?"
  },
  {
    "a": "have x-ray vision?",
    "b": "have magnified hearing?"
  },
  {
    "a": "work in a group?",
    "b": "work alone?"
  }
]
